dlgo/__init__.py
dlgo/checkpoint.py
dlgo/elo.py
dlgo/goboard.py
dlgo/goboard_fast.py
dlgo/goboard_fast_test.py
dlgo/goboard_slow.py
dlgo/goboard_test.py
dlgo/gotypes.py
dlgo/kerasutil.py
dlgo/scoring.py
dlgo/scoring_test.py
dlgo/utils.py
dlgo/zobrist.py
dlgo/agent/__init__.py
dlgo/agent/alphago.py
dlgo/agent/alphago_tst.py
dlgo/agent/base.py
dlgo/agent/helpers.py
dlgo/agent/helpers_fast.py
dlgo/agent/helpers_test.py
dlgo/agent/naive.py
dlgo/agent/naive_fast.py
dlgo/agent/pg.py
dlgo/agent/predict.py
dlgo/agent/termination.py
dlgo/corpora/__init__.py
dlgo/corpora/archive.py
dlgo/corpora/index.py
dlgo/data/__init__.py
dlgo/data/generator.py
dlgo/data/index_processor.py
dlgo/data/parallel_processor.py
dlgo/data/processor.py
dlgo/data/sampling.py
dlgo/encoders/__init__.py
dlgo/encoders/alphago.py
dlgo/encoders/alphago_test.py
dlgo/encoders/base.py
dlgo/encoders/betago.py
dlgo/encoders/oneplane.py
dlgo/encoders/sevenplane.py
dlgo/encoders/simple.py
dlgo/encoders/utils.py
dlgo/gosgf/__init__.py
dlgo/gosgf/sgf.py
dlgo/gosgf/sgf_grammar.py
dlgo/gosgf/sgf_properties.py
dlgo/gtp/__init__.py
dlgo/gtp/board.py
dlgo/gtp/command.py
dlgo/gtp/frontend.py
dlgo/gtp/play_local.py
dlgo/gtp/response.py
dlgo/gtp/utils.py
dlgo/httpfrontend/__init__.py
dlgo/httpfrontend/server.py
dlgo/mcts/__init__.py
dlgo/mcts/mcts.py
dlgo/minimax/__init__.py
dlgo/minimax/alphabeta.py
dlgo/minimax/depthprune.py
dlgo/minimax/minimax.py
dlgo/networks/__init__.py
dlgo/networks/alphago.py
dlgo/networks/alphago_zero.py
dlgo/networks/fullyconnected.py
dlgo/networks/large.py
dlgo/networks/leaky.py
dlgo/networks/medium.py
dlgo/networks/small.py
dlgo/nn/__init__.py
dlgo/nn/average_digits.py
dlgo/nn/layers.py
dlgo/nn/load_mnist.py
dlgo/nn/network.py
dlgo/nn/run_network.py
dlgo/nn/surface_plot.py
dlgo/rl/__init__.py
dlgo/rl/ac.py
dlgo/rl/ac_pass.py
dlgo/rl/experience.py
dlgo/rl/experience_test.py
dlgo/rl/q.py
dlgo/rl/simulate.py
dlgo-0.2.dist-info/METADATA
dlgo-0.2.dist-info/RECORD
dlgo-0.2.dist-info/WHEEL
dlgo-0.2.dist-info/top_level.txt
